{
  "id": 415766744,
  "node_id": "R_kgDOGMgY2A",
  "name": "doktok-contract",
  "full_name": "doconchain/doktok-contract",
  "private": false,
  "owner": {
    "login": "doconchain",
    "id": 92017854,
    "node_id": "U_kgDOBXwUvg",
    "avatar_url": "https://avatars.githubusercontent.com/u/92017854?v=4",
    "gravatar_id": "",
    "url": "https://api.github.com/users/doconchain",
    "html_url": "https://github.com/doconchain",
    "followers_url": "https://api.github.com/users/doconchain/followers",
    "following_url": "https://api.github.com/users/doconchain/following{/other_user}",
    "gists_url": "https://api.github.com/users/doconchain/gists{/gist_id}",
    "starred_url": "https://api.github.com/users/doconchain/starred{/owner}{/repo}",
    "subscriptions_url": "https://api.github.com/users/doconchain/subscriptions",
    "organizations_url": "https://api.github.com/users/doconchain/orgs",
    "repos_url": "https://api.github.com/users/doconchain/repos",
    "events_url": "https://api.github.com/users/doconchain/events{/privacy}",
    "received_events_url": "https://api.github.com/users/doconchain/received_events",
    "type": "User",
    "site_admin": false
  },
  "html_url": "https://github.com/doconchain/doktok-contract",
  "description": "DOK contract",
  "fork": false,
  "url": "https://api.github.com/repos/doconchain/doktok-contract",
  "forks_url": "https://api.github.com/repos/doconchain/doktok-contract/forks",
  "keys_url": "https://api.github.com/repos/doconchain/doktok-contract/keys{/key_id}",
  "collaborators_url": "https://api.github.com/repos/doconchain/doktok-contract/collaborators{/collaborator}",
  "teams_url": "https://api.github.com/repos/doconchain/doktok-contract/teams",
  "hooks_url": "https://api.github.com/repos/doconchain/doktok-contract/hooks",
  "issue_events_url": "https://api.github.com/repos/doconchain/doktok-contract/issues/events{/number}",
  "events_url": "https://api.github.com/repos/doconchain/doktok-contract/events",
  "assignees_url": "https://api.github.com/repos/doconchain/doktok-contract/assignees{/user}",
  "branches_url": "https://api.github.com/repos/doconchain/doktok-contract/branches{/branch}",
  "tags_url": "https://api.github.com/repos/doconchain/doktok-contract/tags",
  "blobs_url": "https://api.github.com/repos/doconchain/doktok-contract/git/blobs{/sha}",
  "git_tags_url": "https://api.github.com/repos/doconchain/doktok-contract/git/tags{/sha}",
  "git_refs_url": "https://api.github.com/repos/doconchain/doktok-contract/git/refs{/sha}",
  "trees_url": "https://api.github.com/repos/doconchain/doktok-contract/git/trees{/sha}",
  "statuses_url": "https://api.github.com/repos/doconchain/doktok-contract/statuses/{sha}",
  "languages_url": "https://api.github.com/repos/doconchain/doktok-contract/languages",
  "stargazers_url": "https://api.github.com/repos/doconchain/doktok-contract/stargazers",
  "contributors_url": "https://api.github.com/repos/doconchain/doktok-contract/contributors",
  "subscribers_url": "https://api.github.com/repos/doconchain/doktok-contract/subscribers",
  "subscription_url": "https://api.github.com/repos/doconchain/doktok-contract/subscription",
  "commits_url": "https://api.github.com/repos/doconchain/doktok-contract/commits{/sha}",
  "git_commits_url": "https://api.github.com/repos/doconchain/doktok-contract/git/commits{/sha}",
  "comments_url": "https://api.github.com/repos/doconchain/doktok-contract/comments{/number}",
  "issue_comment_url": "https://api.github.com/repos/doconchain/doktok-contract/issues/comments{/number}",
  "contents_url": "https://api.github.com/repos/doconchain/doktok-contract/contents/{+path}",
  "compare_url": "https://api.github.com/repos/doconchain/doktok-contract/compare/{base}...{head}",
  "merges_url": "https://api.github.com/repos/doconchain/doktok-contract/merges",
  "archive_url": "https://api.github.com/repos/doconchain/doktok-contract/{archive_format}{/ref}",
  "downloads_url": "https://api.github.com/repos/doconchain/doktok-contract/downloads",
  "issues_url": "https://api.github.com/repos/doconchain/doktok-contract/issues{/number}",
  "pulls_url": "https://api.github.com/repos/doconchain/doktok-contract/pulls{/number}",
  "milestones_url": "https://api.github.com/repos/doconchain/doktok-contract/milestones{/number}",
  "notifications_url": "https://api.github.com/repos/doconchain/doktok-contract/notifications{?since,all,participating}",
  "labels_url": "https://api.github.com/repos/doconchain/doktok-contract/labels{/name}",
  "releases_url": "https://api.github.com/repos/doconchain/doktok-contract/releases{/id}",
  "deployments_url": "https://api.github.com/repos/doconchain/doktok-contract/deployments",
  "created_at": "2021-10-11T03:29:58Z",
  "updated_at": "2021-10-12T03:34:51Z",
  "pushed_at": "2021-10-11T03:32:58Z",
  "git_url": "git://github.com/doconchain/doktok-contract.git",
  "ssh_url": "git@github.com:doconchain/doktok-contract.git",
  "clone_url": "https://github.com/doconchain/doktok-contract.git",
  "svn_url": "https://github.com/doconchain/doktok-contract",
  "homepage": null,
  "size": 4,
  "stargazers_count": 0,
  "watchers_count": 0,
  "language": "Solidity",
  "has_issues": true,
  "has_projects": true,
  "has_downloads": true,
  "has_wiki": true,
  "has_pages": false,
  "forks_count": 1,
  "mirror_url": null,
  "archived": false,
  "disabled": false,
  "open_issues_count": 0,
  "license": null,
  "allow_forking": true,
  "is_template": false,
  "topics": [

  ],
  "visibility": "public",
  "forks": 1,
  "open_issues": 0,
  "watchers": 0,
  "default_branch": "main",
  "permissions": {
    "admin": false,
    "maintain": false,
    "push": false,
    "triage": false,
    "pull": true
  },
  "temp_clone_token": "",
  "network_count": 1,
  "subscribers_count": 1
}