{
  "id": 417242210,
  "node_id": "R_kgDOGN6cYg",
  "name": "EverFight",
  "full_name": "EverFight1/EverFight",
  "private": false,
  "owner": {
    "login": "EverFight1",
    "id": 92522112,
    "node_id": "U_kgDOBYPGgA",
    "avatar_url": "https://avatars.githubusercontent.com/u/92522112?v=4",
    "gravatar_id": "",
    "url": "https://api.github.com/users/EverFight1",
    "html_url": "https://github.com/EverFight1",
    "followers_url": "https://api.github.com/users/EverFight1/followers",
    "following_url": "https://api.github.com/users/EverFight1/following{/other_user}",
    "gists_url": "https://api.github.com/users/EverFight1/gists{/gist_id}",
    "starred_url": "https://api.github.com/users/EverFight1/starred{/owner}{/repo}",
    "subscriptions_url": "https://api.github.com/users/EverFight1/subscriptions",
    "organizations_url": "https://api.github.com/users/EverFight1/orgs",
    "repos_url": "https://api.github.com/users/EverFight1/repos",
    "events_url": "https://api.github.com/users/EverFight1/events{/privacy}",
    "received_events_url": "https://api.github.com/users/EverFight1/received_events",
    "type": "User",
    "site_admin": false
  },
  "html_url": "https://github.com/EverFight1/EverFight",
  "description": null,
  "fork": false,
  "url": "https://api.github.com/repos/EverFight1/EverFight",
  "forks_url": "https://api.github.com/repos/EverFight1/EverFight/forks",
  "keys_url": "https://api.github.com/repos/EverFight1/EverFight/keys{/key_id}",
  "collaborators_url": "https://api.github.com/repos/EverFight1/EverFight/collaborators{/collaborator}",
  "teams_url": "https://api.github.com/repos/EverFight1/EverFight/teams",
  "hooks_url": "https://api.github.com/repos/EverFight1/EverFight/hooks",
  "issue_events_url": "https://api.github.com/repos/EverFight1/EverFight/issues/events{/number}",
  "events_url": "https://api.github.com/repos/EverFight1/EverFight/events",
  "assignees_url": "https://api.github.com/repos/EverFight1/EverFight/assignees{/user}",
  "branches_url": "https://api.github.com/repos/EverFight1/EverFight/branches{/branch}",
  "tags_url": "https://api.github.com/repos/EverFight1/EverFight/tags",
  "blobs_url": "https://api.github.com/repos/EverFight1/EverFight/git/blobs{/sha}",
  "git_tags_url": "https://api.github.com/repos/EverFight1/EverFight/git/tags{/sha}",
  "git_refs_url": "https://api.github.com/repos/EverFight1/EverFight/git/refs{/sha}",
  "trees_url": "https://api.github.com/repos/EverFight1/EverFight/git/trees{/sha}",
  "statuses_url": "https://api.github.com/repos/EverFight1/EverFight/statuses/{sha}",
  "languages_url": "https://api.github.com/repos/EverFight1/EverFight/languages",
  "stargazers_url": "https://api.github.com/repos/EverFight1/EverFight/stargazers",
  "contributors_url": "https://api.github.com/repos/EverFight1/EverFight/contributors",
  "subscribers_url": "https://api.github.com/repos/EverFight1/EverFight/subscribers",
  "subscription_url": "https://api.github.com/repos/EverFight1/EverFight/subscription",
  "commits_url": "https://api.github.com/repos/EverFight1/EverFight/commits{/sha}",
  "git_commits_url": "https://api.github.com/repos/EverFight1/EverFight/git/commits{/sha}",
  "comments_url": "https://api.github.com/repos/EverFight1/EverFight/comments{/number}",
  "issue_comment_url": "https://api.github.com/repos/EverFight1/EverFight/issues/comments{/number}",
  "contents_url": "https://api.github.com/repos/EverFight1/EverFight/contents/{+path}",
  "compare_url": "https://api.github.com/repos/EverFight1/EverFight/compare/{base}...{head}",
  "merges_url": "https://api.github.com/repos/EverFight1/EverFight/merges",
  "archive_url": "https://api.github.com/repos/EverFight1/EverFight/{archive_format}{/ref}",
  "downloads_url": "https://api.github.com/repos/EverFight1/EverFight/downloads",
  "issues_url": "https://api.github.com/repos/EverFight1/EverFight/issues{/number}",
  "pulls_url": "https://api.github.com/repos/EverFight1/EverFight/pulls{/number}",
  "milestones_url": "https://api.github.com/repos/EverFight1/EverFight/milestones{/number}",
  "notifications_url": "https://api.github.com/repos/EverFight1/EverFight/notifications{?since,all,participating}",
  "labels_url": "https://api.github.com/repos/EverFight1/EverFight/labels{/name}",
  "releases_url": "https://api.github.com/repos/EverFight1/EverFight/releases{/id}",
  "deployments_url": "https://api.github.com/repos/EverFight1/EverFight/deployments",
  "created_at": "2021-10-14T18:31:54Z",
  "updated_at": "2021-10-14T18:33:50Z",
  "pushed_at": "2021-10-14T18:33:46Z",
  "git_url": "git://github.com/EverFight1/EverFight.git",
  "ssh_url": "git@github.com:EverFight1/EverFight.git",
  "clone_url": "https://github.com/EverFight1/EverFight.git",
  "svn_url": "https://github.com/EverFight1/EverFight",
  "homepage": null,
  "size": 2170,
  "stargazers_count": 0,
  "watchers_count": 0,
  "language": "Solidity",
  "has_issues": true,
  "has_projects": true,
  "has_downloads": true,
  "has_wiki": true,
  "has_pages": false,
  "forks_count": 0,
  "mirror_url": null,
  "archived": false,
  "disabled": false,
  "open_issues_count": 0,
  "license": null,
  "allow_forking": true,
  "is_template": false,
  "topics": [

  ],
  "visibility": "public",
  "forks": 0,
  "open_issues": 0,
  "watchers": 0,
  "default_branch": "main",
  "permissions": {
    "admin": false,
    "maintain": false,
    "push": false,
    "triage": false,
    "pull": true
  },
  "temp_clone_token": "",
  "network_count": 0,
  "subscribers_count": 1
}