{
  "id": 402731356,
  "node_id": "MDEwOlJlcG9zaXRvcnk0MDI3MzEzNTY=",
  "name": "galaxynetwork",
  "full_name": "gnc-project/galaxynetwork",
  "private": false,
  "owner": {
    "login": "gnc-project",
    "id": 69964481,
    "node_id": "MDQ6VXNlcjY5OTY0NDgx",
    "avatar_url": "https://avatars.githubusercontent.com/u/69964481?v=4",
    "gravatar_id": "",
    "url": "https://api.github.com/users/gnc-project",
    "html_url": "https://github.com/gnc-project",
    "followers_url": "https://api.github.com/users/gnc-project/followers",
    "following_url": "https://api.github.com/users/gnc-project/following{/other_user}",
    "gists_url": "https://api.github.com/users/gnc-project/gists{/gist_id}",
    "starred_url": "https://api.github.com/users/gnc-project/starred{/owner}{/repo}",
    "subscriptions_url": "https://api.github.com/users/gnc-project/subscriptions",
    "organizations_url": "https://api.github.com/users/gnc-project/orgs",
    "repos_url": "https://api.github.com/users/gnc-project/repos",
    "events_url": "https://api.github.com/users/gnc-project/events{/privacy}",
    "received_events_url": "https://api.github.com/users/gnc-project/received_events",
    "type": "User",
    "site_admin": false
  },
  "html_url": "https://github.com/gnc-project/galaxynetwork",
  "description": "galaxynetwork",
  "fork": false,
  "url": "https://api.github.com/repos/gnc-project/galaxynetwork",
  "forks_url": "https://api.github.com/repos/gnc-project/galaxynetwork/forks",
  "keys_url": "https://api.github.com/repos/gnc-project/galaxynetwork/keys{/key_id}",
  "collaborators_url": "https://api.github.com/repos/gnc-project/galaxynetwork/collaborators{/collaborator}",
  "teams_url": "https://api.github.com/repos/gnc-project/galaxynetwork/teams",
  "hooks_url": "https://api.github.com/repos/gnc-project/galaxynetwork/hooks",
  "issue_events_url": "https://api.github.com/repos/gnc-project/galaxynetwork/issues/events{/number}",
  "events_url": "https://api.github.com/repos/gnc-project/galaxynetwork/events",
  "assignees_url": "https://api.github.com/repos/gnc-project/galaxynetwork/assignees{/user}",
  "branches_url": "https://api.github.com/repos/gnc-project/galaxynetwork/branches{/branch}",
  "tags_url": "https://api.github.com/repos/gnc-project/galaxynetwork/tags",
  "blobs_url": "https://api.github.com/repos/gnc-project/galaxynetwork/git/blobs{/sha}",
  "git_tags_url": "https://api.github.com/repos/gnc-project/galaxynetwork/git/tags{/sha}",
  "git_refs_url": "https://api.github.com/repos/gnc-project/galaxynetwork/git/refs{/sha}",
  "trees_url": "https://api.github.com/repos/gnc-project/galaxynetwork/git/trees{/sha}",
  "statuses_url": "https://api.github.com/repos/gnc-project/galaxynetwork/statuses/{sha}",
  "languages_url": "https://api.github.com/repos/gnc-project/galaxynetwork/languages",
  "stargazers_url": "https://api.github.com/repos/gnc-project/galaxynetwork/stargazers",
  "contributors_url": "https://api.github.com/repos/gnc-project/galaxynetwork/contributors",
  "subscribers_url": "https://api.github.com/repos/gnc-project/galaxynetwork/subscribers",
  "subscription_url": "https://api.github.com/repos/gnc-project/galaxynetwork/subscription",
  "commits_url": "https://api.github.com/repos/gnc-project/galaxynetwork/commits{/sha}",
  "git_commits_url": "https://api.github.com/repos/gnc-project/galaxynetwork/git/commits{/sha}",
  "comments_url": "https://api.github.com/repos/gnc-project/galaxynetwork/comments{/number}",
  "issue_comment_url": "https://api.github.com/repos/gnc-project/galaxynetwork/issues/comments{/number}",
  "contents_url": "https://api.github.com/repos/gnc-project/galaxynetwork/contents/{+path}",
  "compare_url": "https://api.github.com/repos/gnc-project/galaxynetwork/compare/{base}...{head}",
  "merges_url": "https://api.github.com/repos/gnc-project/galaxynetwork/merges",
  "archive_url": "https://api.github.com/repos/gnc-project/galaxynetwork/{archive_format}{/ref}",
  "downloads_url": "https://api.github.com/repos/gnc-project/galaxynetwork/downloads",
  "issues_url": "https://api.github.com/repos/gnc-project/galaxynetwork/issues{/number}",
  "pulls_url": "https://api.github.com/repos/gnc-project/galaxynetwork/pulls{/number}",
  "milestones_url": "https://api.github.com/repos/gnc-project/galaxynetwork/milestones{/number}",
  "notifications_url": "https://api.github.com/repos/gnc-project/galaxynetwork/notifications{?since,all,participating}",
  "labels_url": "https://api.github.com/repos/gnc-project/galaxynetwork/labels{/name}",
  "releases_url": "https://api.github.com/repos/gnc-project/galaxynetwork/releases{/id}",
  "deployments_url": "https://api.github.com/repos/gnc-project/galaxynetwork/deployments",
  "created_at": "2021-09-03T10:27:45Z",
  "updated_at": "2021-11-29T09:17:59Z",
  "pushed_at": "2021-11-29T09:19:32Z",
  "git_url": "git://github.com/gnc-project/galaxynetwork.git",
  "ssh_url": "git@github.com:gnc-project/galaxynetwork.git",
  "clone_url": "https://github.com/gnc-project/galaxynetwork.git",
  "svn_url": "https://github.com/gnc-project/galaxynetwork",
  "homepage": null,
  "size": 167075,
  "stargazers_count": 1,
  "watchers_count": 1,
  "language": "Go",
  "has_issues": true,
  "has_projects": true,
  "has_downloads": true,
  "has_wiki": true,
  "has_pages": false,
  "forks_count": 0,
  "mirror_url": null,
  "archived": false,
  "disabled": false,
  "open_issues_count": 0,
  "license": {
    "key": "lgpl-3.0",
    "name": "GNU Lesser General Public License v3.0",
    "spdx_id": "LGPL-3.0",
    "url": "https://api.github.com/licenses/lgpl-3.0",
    "node_id": "MDc6TGljZW5zZTEy"
  },
  "allow_forking": true,
  "is_template": false,
  "topics": [

  ],
  "visibility": "public",
  "forks": 0,
  "open_issues": 0,
  "watchers": 1,
  "default_branch": "master",
  "permissions": {
    "admin": false,
    "maintain": false,
    "push": false,
    "triage": false,
    "pull": true
  },
  "temp_clone_token": "",
  "network_count": 0,
  "subscribers_count": 1
}