{
  "id": 423046881,
  "node_id": "R_kgDOGTcu4Q",
  "name": "Infomatix",
  "full_name": "infomatixDev/Infomatix",
  "private": false,
  "owner": {
    "login": "infomatixDev",
    "id": 93460204,
    "node_id": "O_kgDOBZIW7A",
    "avatar_url": "https://avatars.githubusercontent.com/u/93460204?v=4",
    "gravatar_id": "",
    "url": "https://api.github.com/users/infomatixDev",
    "html_url": "https://github.com/infomatixDev",
    "followers_url": "https://api.github.com/users/infomatixDev/followers",
    "following_url": "https://api.github.com/users/infomatixDev/following{/other_user}",
    "gists_url": "https://api.github.com/users/infomatixDev/gists{/gist_id}",
    "starred_url": "https://api.github.com/users/infomatixDev/starred{/owner}{/repo}",
    "subscriptions_url": "https://api.github.com/users/infomatixDev/subscriptions",
    "organizations_url": "https://api.github.com/users/infomatixDev/orgs",
    "repos_url": "https://api.github.com/users/infomatixDev/repos",
    "events_url": "https://api.github.com/users/infomatixDev/events{/privacy}",
    "received_events_url": "https://api.github.com/users/infomatixDev/received_events",
    "type": "Organization",
    "site_admin": false
  },
  "html_url": "https://github.com/infomatixDev/Infomatix",
  "description": "Infomatix collects and distributes crowdsourced asset data. The Infomatix platform links experts to requests, allowing them to monetize their expertise and provide information to the requesters . The project's aim is to democratise financial data which previously was available only to institutions.",
  "fork": false,
  "url": "https://api.github.com/repos/infomatixDev/Infomatix",
  "forks_url": "https://api.github.com/repos/infomatixDev/Infomatix/forks",
  "keys_url": "https://api.github.com/repos/infomatixDev/Infomatix/keys{/key_id}",
  "collaborators_url": "https://api.github.com/repos/infomatixDev/Infomatix/collaborators{/collaborator}",
  "teams_url": "https://api.github.com/repos/infomatixDev/Infomatix/teams",
  "hooks_url": "https://api.github.com/repos/infomatixDev/Infomatix/hooks",
  "issue_events_url": "https://api.github.com/repos/infomatixDev/Infomatix/issues/events{/number}",
  "events_url": "https://api.github.com/repos/infomatixDev/Infomatix/events",
  "assignees_url": "https://api.github.com/repos/infomatixDev/Infomatix/assignees{/user}",
  "branches_url": "https://api.github.com/repos/infomatixDev/Infomatix/branches{/branch}",
  "tags_url": "https://api.github.com/repos/infomatixDev/Infomatix/tags",
  "blobs_url": "https://api.github.com/repos/infomatixDev/Infomatix/git/blobs{/sha}",
  "git_tags_url": "https://api.github.com/repos/infomatixDev/Infomatix/git/tags{/sha}",
  "git_refs_url": "https://api.github.com/repos/infomatixDev/Infomatix/git/refs{/sha}",
  "trees_url": "https://api.github.com/repos/infomatixDev/Infomatix/git/trees{/sha}",
  "statuses_url": "https://api.github.com/repos/infomatixDev/Infomatix/statuses/{sha}",
  "languages_url": "https://api.github.com/repos/infomatixDev/Infomatix/languages",
  "stargazers_url": "https://api.github.com/repos/infomatixDev/Infomatix/stargazers",
  "contributors_url": "https://api.github.com/repos/infomatixDev/Infomatix/contributors",
  "subscribers_url": "https://api.github.com/repos/infomatixDev/Infomatix/subscribers",
  "subscription_url": "https://api.github.com/repos/infomatixDev/Infomatix/subscription",
  "commits_url": "https://api.github.com/repos/infomatixDev/Infomatix/commits{/sha}",
  "git_commits_url": "https://api.github.com/repos/infomatixDev/Infomatix/git/commits{/sha}",
  "comments_url": "https://api.github.com/repos/infomatixDev/Infomatix/comments{/number}",
  "issue_comment_url": "https://api.github.com/repos/infomatixDev/Infomatix/issues/comments{/number}",
  "contents_url": "https://api.github.com/repos/infomatixDev/Infomatix/contents/{+path}",
  "compare_url": "https://api.github.com/repos/infomatixDev/Infomatix/compare/{base}...{head}",
  "merges_url": "https://api.github.com/repos/infomatixDev/Infomatix/merges",
  "archive_url": "https://api.github.com/repos/infomatixDev/Infomatix/{archive_format}{/ref}",
  "downloads_url": "https://api.github.com/repos/infomatixDev/Infomatix/downloads",
  "issues_url": "https://api.github.com/repos/infomatixDev/Infomatix/issues{/number}",
  "pulls_url": "https://api.github.com/repos/infomatixDev/Infomatix/pulls{/number}",
  "milestones_url": "https://api.github.com/repos/infomatixDev/Infomatix/milestones{/number}",
  "notifications_url": "https://api.github.com/repos/infomatixDev/Infomatix/notifications{?since,all,participating}",
  "labels_url": "https://api.github.com/repos/infomatixDev/Infomatix/labels{/name}",
  "releases_url": "https://api.github.com/repos/infomatixDev/Infomatix/releases{/id}",
  "deployments_url": "https://api.github.com/repos/infomatixDev/Infomatix/deployments",
  "created_at": "2021-10-31T03:52:47Z",
  "updated_at": "2021-11-03T07:55:30Z",
  "pushed_at": "2021-10-31T03:52:56Z",
  "git_url": "git://github.com/infomatixDev/Infomatix.git",
  "ssh_url": "git@github.com:infomatixDev/Infomatix.git",
  "clone_url": "https://github.com/infomatixDev/Infomatix.git",
  "svn_url": "https://github.com/infomatixDev/Infomatix",
  "homepage": "",
  "size": 11,
  "stargazers_count": 1,
  "watchers_count": 1,
  "language": "Solidity",
  "has_issues": true,
  "has_projects": true,
  "has_downloads": true,
  "has_wiki": true,
  "has_pages": false,
  "forks_count": 0,
  "mirror_url": null,
  "archived": false,
  "disabled": false,
  "open_issues_count": 0,
  "license": null,
  "allow_forking": true,
  "is_template": false,
  "topics": [

  ],
  "visibility": "public",
  "forks": 0,
  "open_issues": 0,
  "watchers": 1,
  "default_branch": "main",
  "permissions": {
    "admin": false,
    "maintain": false,
    "push": false,
    "triage": false,
    "pull": true
  },
  "temp_clone_token": "",
  "organization": {
    "login": "infomatixDev",
    "id": 93460204,
    "node_id": "O_kgDOBZIW7A",
    "avatar_url": "https://avatars.githubusercontent.com/u/93460204?v=4",
    "gravatar_id": "",
    "url": "https://api.github.com/users/infomatixDev",
    "html_url": "https://github.com/infomatixDev",
    "followers_url": "https://api.github.com/users/infomatixDev/followers",
    "following_url": "https://api.github.com/users/infomatixDev/following{/other_user}",
    "gists_url": "https://api.github.com/users/infomatixDev/gists{/gist_id}",
    "starred_url": "https://api.github.com/users/infomatixDev/starred{/owner}{/repo}",
    "subscriptions_url": "https://api.github.com/users/infomatixDev/subscriptions",
    "organizations_url": "https://api.github.com/users/infomatixDev/orgs",
    "repos_url": "https://api.github.com/users/infomatixDev/repos",
    "events_url": "https://api.github.com/users/infomatixDev/events{/privacy}",
    "received_events_url": "https://api.github.com/users/infomatixDev/received_events",
    "type": "Organization",
    "site_admin": false
  },
  "network_count": 0,
  "subscribers_count": 0
}