{
  "id": 141525314,
  "node_id": "MDEwOlJlcG9zaXRvcnkxNDE1MjUzMTQ=",
  "name": "BackendSystem",
  "full_name": "Inmediate/BackendSystem",
  "private": false,
  "owner": {
    "login": "Inmediate",
    "id": 41408995,
    "node_id": "MDQ6VXNlcjQxNDA4OTk1",
    "avatar_url": "https://avatars.githubusercontent.com/u/41408995?v=4",
    "gravatar_id": "",
    "url": "https://api.github.com/users/Inmediate",
    "html_url": "https://github.com/Inmediate",
    "followers_url": "https://api.github.com/users/Inmediate/followers",
    "following_url": "https://api.github.com/users/Inmediate/following{/other_user}",
    "gists_url": "https://api.github.com/users/Inmediate/gists{/gist_id}",
    "starred_url": "https://api.github.com/users/Inmediate/starred{/owner}{/repo}",
    "subscriptions_url": "https://api.github.com/users/Inmediate/subscriptions",
    "organizations_url": "https://api.github.com/users/Inmediate/orgs",
    "repos_url": "https://api.github.com/users/Inmediate/repos",
    "events_url": "https://api.github.com/users/Inmediate/events{/privacy}",
    "received_events_url": "https://api.github.com/users/Inmediate/received_events",
    "type": "User",
    "site_admin": false
  },
  "html_url": "https://github.com/Inmediate/BackendSystem",
  "description": "Backend System to connect to insurance provider through API",
  "fork": false,
  "url": "https://api.github.com/repos/Inmediate/BackendSystem",
  "forks_url": "https://api.github.com/repos/Inmediate/BackendSystem/forks",
  "keys_url": "https://api.github.com/repos/Inmediate/BackendSystem/keys{/key_id}",
  "collaborators_url": "https://api.github.com/repos/Inmediate/BackendSystem/collaborators{/collaborator}",
  "teams_url": "https://api.github.com/repos/Inmediate/BackendSystem/teams",
  "hooks_url": "https://api.github.com/repos/Inmediate/BackendSystem/hooks",
  "issue_events_url": "https://api.github.com/repos/Inmediate/BackendSystem/issues/events{/number}",
  "events_url": "https://api.github.com/repos/Inmediate/BackendSystem/events",
  "assignees_url": "https://api.github.com/repos/Inmediate/BackendSystem/assignees{/user}",
  "branches_url": "https://api.github.com/repos/Inmediate/BackendSystem/branches{/branch}",
  "tags_url": "https://api.github.com/repos/Inmediate/BackendSystem/tags",
  "blobs_url": "https://api.github.com/repos/Inmediate/BackendSystem/git/blobs{/sha}",
  "git_tags_url": "https://api.github.com/repos/Inmediate/BackendSystem/git/tags{/sha}",
  "git_refs_url": "https://api.github.com/repos/Inmediate/BackendSystem/git/refs{/sha}",
  "trees_url": "https://api.github.com/repos/Inmediate/BackendSystem/git/trees{/sha}",
  "statuses_url": "https://api.github.com/repos/Inmediate/BackendSystem/statuses/{sha}",
  "languages_url": "https://api.github.com/repos/Inmediate/BackendSystem/languages",
  "stargazers_url": "https://api.github.com/repos/Inmediate/BackendSystem/stargazers",
  "contributors_url": "https://api.github.com/repos/Inmediate/BackendSystem/contributors",
  "subscribers_url": "https://api.github.com/repos/Inmediate/BackendSystem/subscribers",
  "subscription_url": "https://api.github.com/repos/Inmediate/BackendSystem/subscription",
  "commits_url": "https://api.github.com/repos/Inmediate/BackendSystem/commits{/sha}",
  "git_commits_url": "https://api.github.com/repos/Inmediate/BackendSystem/git/commits{/sha}",
  "comments_url": "https://api.github.com/repos/Inmediate/BackendSystem/comments{/number}",
  "issue_comment_url": "https://api.github.com/repos/Inmediate/BackendSystem/issues/comments{/number}",
  "contents_url": "https://api.github.com/repos/Inmediate/BackendSystem/contents/{+path}",
  "compare_url": "https://api.github.com/repos/Inmediate/BackendSystem/compare/{base}...{head}",
  "merges_url": "https://api.github.com/repos/Inmediate/BackendSystem/merges",
  "archive_url": "https://api.github.com/repos/Inmediate/BackendSystem/{archive_format}{/ref}",
  "downloads_url": "https://api.github.com/repos/Inmediate/BackendSystem/downloads",
  "issues_url": "https://api.github.com/repos/Inmediate/BackendSystem/issues{/number}",
  "pulls_url": "https://api.github.com/repos/Inmediate/BackendSystem/pulls{/number}",
  "milestones_url": "https://api.github.com/repos/Inmediate/BackendSystem/milestones{/number}",
  "notifications_url": "https://api.github.com/repos/Inmediate/BackendSystem/notifications{?since,all,participating}",
  "labels_url": "https://api.github.com/repos/Inmediate/BackendSystem/labels{/name}",
  "releases_url": "https://api.github.com/repos/Inmediate/BackendSystem/releases{/id}",
  "deployments_url": "https://api.github.com/repos/Inmediate/BackendSystem/deployments",
  "created_at": "2018-07-19T04:41:54Z",
  "updated_at": "2018-08-23T04:00:40Z",
  "pushed_at": "2018-07-19T05:15:55Z",
  "git_url": "git://github.com/Inmediate/BackendSystem.git",
  "ssh_url": "git@github.com:Inmediate/BackendSystem.git",
  "clone_url": "https://github.com/Inmediate/BackendSystem.git",
  "svn_url": "https://github.com/Inmediate/BackendSystem",
  "homepage": null,
  "size": 180,
  "stargazers_count": 2,
  "watchers_count": 2,
  "language": "Ruby",
  "has_issues": true,
  "has_projects": true,
  "has_downloads": true,
  "has_wiki": true,
  "has_pages": false,
  "forks_count": 1,
  "mirror_url": null,
  "archived": false,
  "disabled": false,
  "open_issues_count": 0,
  "license": null,
  "allow_forking": true,
  "is_template": false,
  "topics": [

  ],
  "visibility": "public",
  "forks": 1,
  "open_issues": 0,
  "watchers": 2,
  "default_branch": "master",
  "permissions": {
    "admin": false,
    "maintain": false,
    "push": false,
    "triage": false,
    "pull": true
  },
  "temp_clone_token": "",
  "network_count": 1,
  "subscribers_count": 5
}