{
  "id": 117904739,
  "node_id": "MDEwOlJlcG9zaXRvcnkxMTc5MDQ3Mzk=",
  "name": "Nasdacoin",
  "full_name": "Nasdacoin/Nasdacoin",
  "private": false,
  "owner": {
    "login": "Nasdacoin",
    "id": 35544028,
    "node_id": "MDQ6VXNlcjM1NTQ0MDI4",
    "avatar_url": "https://avatars.githubusercontent.com/u/35544028?v=4",
    "gravatar_id": "",
    "url": "https://api.github.com/users/Nasdacoin",
    "html_url": "https://github.com/Nasdacoin",
    "followers_url": "https://api.github.com/users/Nasdacoin/followers",
    "following_url": "https://api.github.com/users/Nasdacoin/following{/other_user}",
    "gists_url": "https://api.github.com/users/Nasdacoin/gists{/gist_id}",
    "starred_url": "https://api.github.com/users/Nasdacoin/starred{/owner}{/repo}",
    "subscriptions_url": "https://api.github.com/users/Nasdacoin/subscriptions",
    "organizations_url": "https://api.github.com/users/Nasdacoin/orgs",
    "repos_url": "https://api.github.com/users/Nasdacoin/repos",
    "events_url": "https://api.github.com/users/Nasdacoin/events{/privacy}",
    "received_events_url": "https://api.github.com/users/Nasdacoin/received_events",
    "type": "User",
    "site_admin": false
  },
  "html_url": "https://github.com/Nasdacoin/Nasdacoin",
  "description": null,
  "fork": false,
  "url": "https://api.github.com/repos/Nasdacoin/Nasdacoin",
  "forks_url": "https://api.github.com/repos/Nasdacoin/Nasdacoin/forks",
  "keys_url": "https://api.github.com/repos/Nasdacoin/Nasdacoin/keys{/key_id}",
  "collaborators_url": "https://api.github.com/repos/Nasdacoin/Nasdacoin/collaborators{/collaborator}",
  "teams_url": "https://api.github.com/repos/Nasdacoin/Nasdacoin/teams",
  "hooks_url": "https://api.github.com/repos/Nasdacoin/Nasdacoin/hooks",
  "issue_events_url": "https://api.github.com/repos/Nasdacoin/Nasdacoin/issues/events{/number}",
  "events_url": "https://api.github.com/repos/Nasdacoin/Nasdacoin/events",
  "assignees_url": "https://api.github.com/repos/Nasdacoin/Nasdacoin/assignees{/user}",
  "branches_url": "https://api.github.com/repos/Nasdacoin/Nasdacoin/branches{/branch}",
  "tags_url": "https://api.github.com/repos/Nasdacoin/Nasdacoin/tags",
  "blobs_url": "https://api.github.com/repos/Nasdacoin/Nasdacoin/git/blobs{/sha}",
  "git_tags_url": "https://api.github.com/repos/Nasdacoin/Nasdacoin/git/tags{/sha}",
  "git_refs_url": "https://api.github.com/repos/Nasdacoin/Nasdacoin/git/refs{/sha}",
  "trees_url": "https://api.github.com/repos/Nasdacoin/Nasdacoin/git/trees{/sha}",
  "statuses_url": "https://api.github.com/repos/Nasdacoin/Nasdacoin/statuses/{sha}",
  "languages_url": "https://api.github.com/repos/Nasdacoin/Nasdacoin/languages",
  "stargazers_url": "https://api.github.com/repos/Nasdacoin/Nasdacoin/stargazers",
  "contributors_url": "https://api.github.com/repos/Nasdacoin/Nasdacoin/contributors",
  "subscribers_url": "https://api.github.com/repos/Nasdacoin/Nasdacoin/subscribers",
  "subscription_url": "https://api.github.com/repos/Nasdacoin/Nasdacoin/subscription",
  "commits_url": "https://api.github.com/repos/Nasdacoin/Nasdacoin/commits{/sha}",
  "git_commits_url": "https://api.github.com/repos/Nasdacoin/Nasdacoin/git/commits{/sha}",
  "comments_url": "https://api.github.com/repos/Nasdacoin/Nasdacoin/comments{/number}",
  "issue_comment_url": "https://api.github.com/repos/Nasdacoin/Nasdacoin/issues/comments{/number}",
  "contents_url": "https://api.github.com/repos/Nasdacoin/Nasdacoin/contents/{+path}",
  "compare_url": "https://api.github.com/repos/Nasdacoin/Nasdacoin/compare/{base}...{head}",
  "merges_url": "https://api.github.com/repos/Nasdacoin/Nasdacoin/merges",
  "archive_url": "https://api.github.com/repos/Nasdacoin/Nasdacoin/{archive_format}{/ref}",
  "downloads_url": "https://api.github.com/repos/Nasdacoin/Nasdacoin/downloads",
  "issues_url": "https://api.github.com/repos/Nasdacoin/Nasdacoin/issues{/number}",
  "pulls_url": "https://api.github.com/repos/Nasdacoin/Nasdacoin/pulls{/number}",
  "milestones_url": "https://api.github.com/repos/Nasdacoin/Nasdacoin/milestones{/number}",
  "notifications_url": "https://api.github.com/repos/Nasdacoin/Nasdacoin/notifications{?since,all,participating}",
  "labels_url": "https://api.github.com/repos/Nasdacoin/Nasdacoin/labels{/name}",
  "releases_url": "https://api.github.com/repos/Nasdacoin/Nasdacoin/releases{/id}",
  "deployments_url": "https://api.github.com/repos/Nasdacoin/Nasdacoin/deployments",
  "created_at": "2018-01-17T23:21:25Z",
  "updated_at": "2021-04-20T23:12:10Z",
  "pushed_at": "2019-11-10T05:22:00Z",
  "git_url": "git://github.com/Nasdacoin/Nasdacoin.git",
  "ssh_url": "git@github.com:Nasdacoin/Nasdacoin.git",
  "clone_url": "https://github.com/Nasdacoin/Nasdacoin.git",
  "svn_url": "https://github.com/Nasdacoin/Nasdacoin",
  "homepage": null,
  "size": 1334,
  "stargazers_count": 11,
  "watchers_count": 11,
  "language": "C++",
  "has_issues": true,
  "has_projects": true,
  "has_downloads": true,
  "has_wiki": true,
  "has_pages": false,
  "forks_count": 10,
  "mirror_url": null,
  "archived": false,
  "disabled": false,
  "open_issues_count": 0,
  "license": {
    "key": "other",
    "name": "Other",
    "spdx_id": "NOASSERTION",
    "url": null,
    "node_id": "MDc6TGljZW5zZTA="
  },
  "allow_forking": true,
  "is_template": false,
  "topics": [

  ],
  "visibility": "public",
  "forks": 10,
  "open_issues": 0,
  "watchers": 11,
  "default_branch": "master",
  "permissions": {
    "admin": false,
    "maintain": false,
    "push": false,
    "triage": false,
    "pull": true
  },
  "temp_clone_token": "",
  "network_count": 10,
  "subscribers_count": 4
}