{
  "id": 422507552,
  "node_id": "R_kgDOGS70IA",
  "name": "Drachma",
  "full_name": "Nikethedike1/Drachma",
  "private": false,
  "owner": {
    "login": "Nikethedike1",
    "id": 93375668,
    "node_id": "U_kgDOBZDMtA",
    "avatar_url": "https://avatars.githubusercontent.com/u/93375668?v=4",
    "gravatar_id": "",
    "url": "https://api.github.com/users/Nikethedike1",
    "html_url": "https://github.com/Nikethedike1",
    "followers_url": "https://api.github.com/users/Nikethedike1/followers",
    "following_url": "https://api.github.com/users/Nikethedike1/following{/other_user}",
    "gists_url": "https://api.github.com/users/Nikethedike1/gists{/gist_id}",
    "starred_url": "https://api.github.com/users/Nikethedike1/starred{/owner}{/repo}",
    "subscriptions_url": "https://api.github.com/users/Nikethedike1/subscriptions",
    "organizations_url": "https://api.github.com/users/Nikethedike1/orgs",
    "repos_url": "https://api.github.com/users/Nikethedike1/repos",
    "events_url": "https://api.github.com/users/Nikethedike1/events{/privacy}",
    "received_events_url": "https://api.github.com/users/Nikethedike1/received_events",
    "type": "User",
    "site_admin": false
  },
  "html_url": "https://github.com/Nikethedike1/Drachma",
  "description": null,
  "fork": false,
  "url": "https://api.github.com/repos/Nikethedike1/Drachma",
  "forks_url": "https://api.github.com/repos/Nikethedike1/Drachma/forks",
  "keys_url": "https://api.github.com/repos/Nikethedike1/Drachma/keys{/key_id}",
  "collaborators_url": "https://api.github.com/repos/Nikethedike1/Drachma/collaborators{/collaborator}",
  "teams_url": "https://api.github.com/repos/Nikethedike1/Drachma/teams",
  "hooks_url": "https://api.github.com/repos/Nikethedike1/Drachma/hooks",
  "issue_events_url": "https://api.github.com/repos/Nikethedike1/Drachma/issues/events{/number}",
  "events_url": "https://api.github.com/repos/Nikethedike1/Drachma/events",
  "assignees_url": "https://api.github.com/repos/Nikethedike1/Drachma/assignees{/user}",
  "branches_url": "https://api.github.com/repos/Nikethedike1/Drachma/branches{/branch}",
  "tags_url": "https://api.github.com/repos/Nikethedike1/Drachma/tags",
  "blobs_url": "https://api.github.com/repos/Nikethedike1/Drachma/git/blobs{/sha}",
  "git_tags_url": "https://api.github.com/repos/Nikethedike1/Drachma/git/tags{/sha}",
  "git_refs_url": "https://api.github.com/repos/Nikethedike1/Drachma/git/refs{/sha}",
  "trees_url": "https://api.github.com/repos/Nikethedike1/Drachma/git/trees{/sha}",
  "statuses_url": "https://api.github.com/repos/Nikethedike1/Drachma/statuses/{sha}",
  "languages_url": "https://api.github.com/repos/Nikethedike1/Drachma/languages",
  "stargazers_url": "https://api.github.com/repos/Nikethedike1/Drachma/stargazers",
  "contributors_url": "https://api.github.com/repos/Nikethedike1/Drachma/contributors",
  "subscribers_url": "https://api.github.com/repos/Nikethedike1/Drachma/subscribers",
  "subscription_url": "https://api.github.com/repos/Nikethedike1/Drachma/subscription",
  "commits_url": "https://api.github.com/repos/Nikethedike1/Drachma/commits{/sha}",
  "git_commits_url": "https://api.github.com/repos/Nikethedike1/Drachma/git/commits{/sha}",
  "comments_url": "https://api.github.com/repos/Nikethedike1/Drachma/comments{/number}",
  "issue_comment_url": "https://api.github.com/repos/Nikethedike1/Drachma/issues/comments{/number}",
  "contents_url": "https://api.github.com/repos/Nikethedike1/Drachma/contents/{+path}",
  "compare_url": "https://api.github.com/repos/Nikethedike1/Drachma/compare/{base}...{head}",
  "merges_url": "https://api.github.com/repos/Nikethedike1/Drachma/merges",
  "archive_url": "https://api.github.com/repos/Nikethedike1/Drachma/{archive_format}{/ref}",
  "downloads_url": "https://api.github.com/repos/Nikethedike1/Drachma/downloads",
  "issues_url": "https://api.github.com/repos/Nikethedike1/Drachma/issues{/number}",
  "pulls_url": "https://api.github.com/repos/Nikethedike1/Drachma/pulls{/number}",
  "milestones_url": "https://api.github.com/repos/Nikethedike1/Drachma/milestones{/number}",
  "notifications_url": "https://api.github.com/repos/Nikethedike1/Drachma/notifications{?since,all,participating}",
  "labels_url": "https://api.github.com/repos/Nikethedike1/Drachma/labels{/name}",
  "releases_url": "https://api.github.com/repos/Nikethedike1/Drachma/releases{/id}",
  "deployments_url": "https://api.github.com/repos/Nikethedike1/Drachma/deployments",
  "created_at": "2021-10-29T08:56:41Z",
  "updated_at": "2021-11-03T05:09:14Z",
  "pushed_at": "2021-10-29T08:56:42Z",
  "git_url": "git://github.com/Nikethedike1/Drachma.git",
  "ssh_url": "git@github.com:Nikethedike1/Drachma.git",
  "clone_url": "https://github.com/Nikethedike1/Drachma.git",
  "svn_url": "https://github.com/Nikethedike1/Drachma",
  "homepage": null,
  "size": 0,
  "stargazers_count": 0,
  "watchers_count": 0,
  "language": null,
  "has_issues": true,
  "has_projects": true,
  "has_downloads": true,
  "has_wiki": true,
  "has_pages": false,
  "forks_count": 0,
  "mirror_url": null,
  "archived": false,
  "disabled": false,
  "open_issues_count": 0,
  "license": null,
  "allow_forking": true,
  "is_template": false,
  "topics": [

  ],
  "visibility": "public",
  "forks": 0,
  "open_issues": 0,
  "watchers": 0,
  "default_branch": "main",
  "permissions": {
    "admin": false,
    "maintain": false,
    "push": false,
    "triage": false,
    "pull": true
  },
  "temp_clone_token": "",
  "network_count": 0,
  "subscribers_count": 1
}