{
  "id": 106261203,
  "node_id": "MDEwOlJlcG9zaXRvcnkxMDYyNjEyMDM=",
  "name": "phantomx",
  "full_name": "phantomxdev/phantomx",
  "private": false,
  "owner": {
    "login": "phantomxdev",
    "id": 32600100,
    "node_id": "MDQ6VXNlcjMyNjAwMTAw",
    "avatar_url": "https://avatars.githubusercontent.com/u/32600100?v=4",
    "gravatar_id": "",
    "url": "https://api.github.com/users/phantomxdev",
    "html_url": "https://github.com/phantomxdev",
    "followers_url": "https://api.github.com/users/phantomxdev/followers",
    "following_url": "https://api.github.com/users/phantomxdev/following{/other_user}",
    "gists_url": "https://api.github.com/users/phantomxdev/gists{/gist_id}",
    "starred_url": "https://api.github.com/users/phantomxdev/starred{/owner}{/repo}",
    "subscriptions_url": "https://api.github.com/users/phantomxdev/subscriptions",
    "organizations_url": "https://api.github.com/users/phantomxdev/orgs",
    "repos_url": "https://api.github.com/users/phantomxdev/repos",
    "events_url": "https://api.github.com/users/phantomxdev/events{/privacy}",
    "received_events_url": "https://api.github.com/users/phantomxdev/received_events",
    "type": "User",
    "site_admin": false
  },
  "html_url": "https://github.com/phantomxdev/phantomx",
  "description": null,
  "fork": false,
  "url": "https://api.github.com/repos/phantomxdev/phantomx",
  "forks_url": "https://api.github.com/repos/phantomxdev/phantomx/forks",
  "keys_url": "https://api.github.com/repos/phantomxdev/phantomx/keys{/key_id}",
  "collaborators_url": "https://api.github.com/repos/phantomxdev/phantomx/collaborators{/collaborator}",
  "teams_url": "https://api.github.com/repos/phantomxdev/phantomx/teams",
  "hooks_url": "https://api.github.com/repos/phantomxdev/phantomx/hooks",
  "issue_events_url": "https://api.github.com/repos/phantomxdev/phantomx/issues/events{/number}",
  "events_url": "https://api.github.com/repos/phantomxdev/phantomx/events",
  "assignees_url": "https://api.github.com/repos/phantomxdev/phantomx/assignees{/user}",
  "branches_url": "https://api.github.com/repos/phantomxdev/phantomx/branches{/branch}",
  "tags_url": "https://api.github.com/repos/phantomxdev/phantomx/tags",
  "blobs_url": "https://api.github.com/repos/phantomxdev/phantomx/git/blobs{/sha}",
  "git_tags_url": "https://api.github.com/repos/phantomxdev/phantomx/git/tags{/sha}",
  "git_refs_url": "https://api.github.com/repos/phantomxdev/phantomx/git/refs{/sha}",
  "trees_url": "https://api.github.com/repos/phantomxdev/phantomx/git/trees{/sha}",
  "statuses_url": "https://api.github.com/repos/phantomxdev/phantomx/statuses/{sha}",
  "languages_url": "https://api.github.com/repos/phantomxdev/phantomx/languages",
  "stargazers_url": "https://api.github.com/repos/phantomxdev/phantomx/stargazers",
  "contributors_url": "https://api.github.com/repos/phantomxdev/phantomx/contributors",
  "subscribers_url": "https://api.github.com/repos/phantomxdev/phantomx/subscribers",
  "subscription_url": "https://api.github.com/repos/phantomxdev/phantomx/subscription",
  "commits_url": "https://api.github.com/repos/phantomxdev/phantomx/commits{/sha}",
  "git_commits_url": "https://api.github.com/repos/phantomxdev/phantomx/git/commits{/sha}",
  "comments_url": "https://api.github.com/repos/phantomxdev/phantomx/comments{/number}",
  "issue_comment_url": "https://api.github.com/repos/phantomxdev/phantomx/issues/comments{/number}",
  "contents_url": "https://api.github.com/repos/phantomxdev/phantomx/contents/{+path}",
  "compare_url": "https://api.github.com/repos/phantomxdev/phantomx/compare/{base}...{head}",
  "merges_url": "https://api.github.com/repos/phantomxdev/phantomx/merges",
  "archive_url": "https://api.github.com/repos/phantomxdev/phantomx/{archive_format}{/ref}",
  "downloads_url": "https://api.github.com/repos/phantomxdev/phantomx/downloads",
  "issues_url": "https://api.github.com/repos/phantomxdev/phantomx/issues{/number}",
  "pulls_url": "https://api.github.com/repos/phantomxdev/phantomx/pulls{/number}",
  "milestones_url": "https://api.github.com/repos/phantomxdev/phantomx/milestones{/number}",
  "notifications_url": "https://api.github.com/repos/phantomxdev/phantomx/notifications{?since,all,participating}",
  "labels_url": "https://api.github.com/repos/phantomxdev/phantomx/labels{/name}",
  "releases_url": "https://api.github.com/repos/phantomxdev/phantomx/releases{/id}",
  "deployments_url": "https://api.github.com/repos/phantomxdev/phantomx/deployments",
  "created_at": "2017-10-09T09:09:53Z",
  "updated_at": "2021-03-03T05:09:30Z",
  "pushed_at": "2019-03-04T07:23:21Z",
  "git_url": "git://github.com/phantomxdev/phantomx.git",
  "ssh_url": "git@github.com:phantomxdev/phantomx.git",
  "clone_url": "https://github.com/phantomxdev/phantomx.git",
  "svn_url": "https://github.com/phantomxdev/phantomx",
  "homepage": null,
  "size": 24741,
  "stargazers_count": 10,
  "watchers_count": 10,
  "language": "Makefile",
  "has_issues": true,
  "has_projects": true,
  "has_downloads": true,
  "has_wiki": true,
  "has_pages": false,
  "forks_count": 11,
  "mirror_url": null,
  "archived": false,
  "disabled": false,
  "open_issues_count": 0,
  "license": null,
  "allow_forking": true,
  "is_template": false,
  "topics": [

  ],
  "visibility": "public",
  "forks": 11,
  "open_issues": 0,
  "watchers": 10,
  "default_branch": "master",
  "permissions": {
    "admin": false,
    "maintain": false,
    "push": false,
    "triage": false,
    "pull": true
  },
  "temp_clone_token": "",
  "network_count": 11,
  "subscribers_count": 10
}